cltk/__init__.py
cltk/__main__.py
cltk/compare_backends.py
cltk/nlp.py
cltk/py.typed
cltk/cli/__init__.py
cltk/cli/analyze.py
cltk/cli/compare.py
cltk/cli/compare_backends.py
cltk/cli/dispatch.py
cltk/cli/export.py
cltk/cli/main.py
cltk/cli/pipeline.py
cltk/cli/utils.py
cltk/core/__init__.py
cltk/core/cltk_logger.py
cltk/core/data_types.py
cltk/core/exceptions.py
cltk/core/logging_utils.py
cltk/core/process_registry.py
cltk/core/provenance.py
cltk/dependency/__init__.py
cltk/dependency/processes.py
cltk/dependency/utils.py
cltk/enrichment/__init__.py
cltk/enrichment/processes.py
cltk/enrichment/utils.py
cltk/evaluation/__init__.py
cltk/evaluation/compare_backends.py
cltk/exports/__init__.py
cltk/exports/_helpers.py
cltk/exports/igt.py
cltk/exports/readers_guide_html.py
cltk/exports/tei.py
cltk/genai/__init__.py
cltk/genai/mistral.py
cltk/genai/ollama.py
cltk/genai/openai.py
cltk/genai/prompt_registry.py
cltk/genai/prompts.py
cltk/languages/__init__.py
cltk/languages/example_texts.py
cltk/languages/glottolog.py
cltk/languages/languages.py
cltk/languages/pipelines.py
cltk/languages/utils.py
cltk/morphosyntax/__init__.py
cltk/morphosyntax/conll.py
cltk/morphosyntax/processes.py
cltk/morphosyntax/ud_deprels.py
cltk/morphosyntax/ud_features.py
cltk/morphosyntax/ud_pos.py
cltk/morphosyntax/utils.py
cltk/pipeline/__init__.py
cltk/pipeline/compiler.py
cltk/pipeline/presets.py
cltk/pipeline/spec_io.py
cltk/pipeline/specs.py
cltk/sentence/__init__.py
cltk/sentence/processes.py
cltk/sentence/utils.py
cltk/stanza/__init__.py
cltk/stanza/processes.py
cltk/text/__init__.py
cltk/text/processes.py
cltk/text/utils.py
cltk/translation/__init__.py
cltk/translation/processes.py
cltk/translation/utils.py
cltk/utils/__init__.py
cltk/utils/file_operations.py
cltk/utils/file_outputs.py
cltk/utils/utils.py
cltk-2.4.0.dist-info/METADATA
cltk-2.4.0.dist-info/WHEEL
cltk-2.4.0.dist-info/entry_points.txt
cltk-2.4.0.dist-info/licenses/LICENSE
cltk-2.4.0.dist-info/RECORD
