Metadata-Version: 2.4
Name: cltk
Version: 2.4.0
Summary: The Classical Language Toolkit
Project-URL: Homepage, http://cltk.org
Project-URL: Repository, https://github.com/cltk/cltk
Project-URL: Documentation, https://docs.cltk.org
Author-email: "Kyle P. Johnson" <kyle@kyle-p-johnson.com>, Clément Besnier <clem@clementbesnier.fr>
License-File: LICENSE
Keywords: ai,arabic,chinese,greek,hebrew,latin,nlp,nltk,sanskrit
Requires-Python: >=3.13
Requires-Dist: colorama<0.5.0,>=0.4.6
Requires-Dist: numpy<3.0.0,>=2.3.2
Requires-Dist: pydantic<3.0.0,>=2.11.7
Requires-Dist: python-dotenv<2.0.0,>=1.1.1
Requires-Dist: tqdm<5.0.0,>=4.67.1
Provides-Extra: mistral
Requires-Dist: mistralai<2.0.0,>=1.9.0; extra == 'mistral'
Provides-Extra: ollama
Requires-Dist: httpx<0.29; extra == 'ollama'
Requires-Dist: ollama<1.0.0,>=0.3.0; extra == 'ollama'
Provides-Extra: openai
Requires-Dist: openai<2.0.0,>=1.101.0; extra == 'openai'
Provides-Extra: stanza
Requires-Dist: stanza<2.0.0,>=1.8.2; extra == 'stanza'
